pylx16a/__init__.py
pylx16a/lx16a.py
pylx16a-1.1.1.dist-info/LICENSE
pylx16a-1.1.1.dist-info/METADATA
pylx16a-1.1.1.dist-info/WHEEL
pylx16a-1.1.1.dist-info/top_level.txt
pylx16a-1.1.1.dist-info/RECORD
